bread/__init__.py
bread/bread.py
bread/utils.py
bread/migrations/0001_initial.py
bread/migrations/0002_delete_breadtestmodel.py
bread/migrations/__init__.py
bread/static/js/URI.js
bread/static/js/bread.js
bread/templates/bread/browse.html
bread/templates/bread/delete.html
bread/templates/bread/edit.html
bread/templates/bread/empty.html
bread/templates/bread/label_value_read.html
bread/templates/bread/read.html
bread/templates/bread/includes/browse.html
bread/templates/bread/includes/delete.html
bread/templates/bread/includes/edit.html
bread/templates/bread/includes/label_value_read.html
bread/templates/bread/includes/read.html
bread/templatetags/__init__.py
bread/templatetags/bread_tags.py
django_bread-1.0.8.dist-info/licenses/LICENSE.txt
tests/__init__.py
tests/base.py
tests/factories.py
tests/models.py
tests/test_add.py
tests/test_browse.py
tests/test_delete.py
tests/test_edit.py
tests/test_filters.py
tests/test_forms.py
tests/test_pagination.py
tests/test_permissions.py
tests/test_read.py
tests/test_search.py
tests/test_templates.py
tests/test_urls.py
tests/test_utils.py
django_bread-1.0.8.dist-info/METADATA
django_bread-1.0.8.dist-info/WHEEL
django_bread-1.0.8.dist-info/top_level.txt
django_bread-1.0.8.dist-info/RECORD
